bsky2llm/__init__.py
bsky2llm/ai_api_call.py
bsky2llm/get_raw_thread.py
bsky2llm/markdown_creator.py
bsky2llm/md_to_openai.py
bsky2llm/process.py
bsky2llm/process_image.py
bsky2llm/process_video.py
bsky2llm/url_converter.py
bsky2llm-0.1.0.dist-info/licenses/LICENSE
bsky2llm-0.1.0.dist-info/METADATA
bsky2llm-0.1.0.dist-info/WHEEL
bsky2llm-0.1.0.dist-info/top_level.txt
bsky2llm-0.1.0.dist-info/RECORD
